autocall/__init__.py
autocall/parser.py
autocall-1.1.1.dist-info/LICENSE.txt
autocall-1.1.1.dist-info/METADATA
autocall-1.1.1.dist-info/WHEEL
autocall-1.1.1.dist-info/top_level.txt
autocall-1.1.1.dist-info/RECORD
