Metadata-Version: 2.1
Name: autocall
Version: 1.1.1
Summary: Call function directly in command line and a well help tips generately automatically
Author-email: bajeer <z_bajer@yeah.net>
Maintainer-email: bajeer <z_bajer@yeah.net>
License: Copyright (c) 2016 The Python Packaging Authority (PyPA)
Project-URL: Homepage, https://gitee.com/z-bajer/autocall
Project-URL: Bug Reports, https://gitee.com/z-bajer/autocall/issues
Project-URL: Source, https://gitee.com/z-bajer/autocall
Keywords: command,line,call,function
Classifier: Development Status :: 3 - Alpha
Classifier: Intended Audience :: Developers
Classifier: Topic :: Software Development
Classifier: License :: OSI Approved :: MIT License
Classifier: Programming Language :: Python :: 3
Classifier: Programming Language :: Python :: 3.8
Classifier: Programming Language :: Python :: 3.9
Classifier: Programming Language :: Python :: 3.10
Classifier: Programming Language :: Python :: 3.11
Classifier: Programming Language :: Python :: 3.12
Classifier: Programming Language :: Python :: 3 :: Only
Requires-Python: >=3.8
License-File: LICENSE.txt
Provides-Extra: dev
Requires-Dist: check-manifest ; extra == 'dev'
Provides-Extra: test
Requires-Dist: coverage ; extra == 'test'
